cutting_stock/__init__.py
cutting_stock/solver.py
cutting_stock/visualization.py
cutting_stock-0.1.3.dist-info/METADATA
cutting_stock-0.1.3.dist-info/WHEEL
cutting_stock-0.1.3.dist-info/entry_points.txt
cutting_stock-0.1.3.dist-info/RECORD
