Metadata-Version: 2.4
Name: cutting-stock
Version: 0.1.3
Summary: A Python implementation of the cutting stock problem solver
Project-URL: Homepage, https://github.com/ionmich/cutting-stock
Project-URL: Repository, https://github.com/ionmich/cutting-stock
Project-URL: Issues, https://github.com/ionmich/cutting-stock/issues
Author-email: Ioannis Michaloliakos <ioannis.michalol@ufl.edu>
License-Expression: MIT
Classifier: Development Status :: 3 - Alpha
Classifier: Intended Audience :: Developers
Classifier: Intended Audience :: Science/Research
Classifier: License :: OSI Approved :: MIT License
Classifier: Programming Language :: Python :: 3
Classifier: Programming Language :: Python :: 3.10
Classifier: Programming Language :: Python :: 3.11
Classifier: Programming Language :: Python :: 3.12
Classifier: Topic :: Scientific/Engineering :: Mathematics
Classifier: Topic :: Software Development :: Libraries :: Python Modules
Requires-Python: >=3.10
Requires-Dist: cvxopt
Requires-Dist: cvxpy
Requires-Dist: numpy
Requires-Dist: scipy
